{"sections":{"multicolumn_7TxFAx":{"type":"multicolumn","blocks":{"column_TCgK7a":{"type":"column","settings":{"image":"shopify:\/\/shop_images\/8901725008895.webp","title":"","text":"","link_label":"Atta","link":"shopify:\/\/collections\/atta-flour"}}},"block_order":["column_TCgK7a"],"settings":{"title":"","heading_size":"h1","image_width":"full","image_ratio":"square","columns_desktop":6,"column_alignment":"center","background_style":"primary","button_label":"","button_link":"","color_scheme":"","columns_mobile":"2","swipe_on_mobile":false,"padding_top":12,"padding_bottom":4}},"banner":{"type":"main-collection-banner","settings":{"show_collection_description":false,"show_collection_image":true,"color_scheme":"scheme-2"}},"product-grid":{"type":"main-collection-product-grid","settings":{"products_per_page":20,"columns_desktop":4,"color_scheme":"scheme-09c8ce1b-9dad-408d-ab20-29ef3b3e28df","image_ratio":"square","image_shape":"default","show_secondary_image":false,"show_vendor":true,"show_rating":false,"quick_add":"bulk","enable_filtering":true,"filter_type":"vertical","enable_sorting":true,"columns_mobile":"2","padding_top":20,"padding_bottom":20}}},"order":["multicolumn_7TxFAx","banner","product-grid"]}